{
    "Name": "Paulie",
    "Set": "OP03-066",
    "Rarity": "SR",
    "Type": "CHARACTER",
    "Image": "https://en.onepiece-cardgame.com/images/cardlist/card/OP03-066_p1.png?231031",
    "Cost": "5",
    "Power": "6000",
    "Color": "Purple",
    "Counter": "-",
    "Attribute": "Strike",
    "Feature": "Water Seven/Galley-La Company",
    "Text": "Effect[On Play] \u2781 (You may rest the specified number of DON!! cards in your cost area.): Add up to 1 DON!! card from your DON!! deck and set it as active. Then, if you have 8 or more DON!! cards on your field, K.O. up to 1 of your opponent's Characters with a cost of 4 or less."
}