{
    "Name": "Let Us Begin the World of Violence!!!",
    "Set": "OP05-059",
    "Rarity": "UC",
    "Type": "EVENT",
    "Image": "https://en.onepiece-cardgame.com/images/cardlist/card/OP05-059.png?231031",
    "Cost": "5",
    "Power": "-",
    "Color": "Blue",
    "Counter": "-",
    "Attribute": "",
    "Feature": "The Four Emperors/Animal Kingdom Pirates",
    "Text": "Effect[Main] If your Leader is multicolored, draw 1 card. Then, return up to 1 Character with a cost of 5 or less to the owner's hand."
}